matrix_completion.py
SML_matrix_completion-0.2.dist-info/METADATA
SML_matrix_completion-0.2.dist-info/WHEEL
SML_matrix_completion-0.2.dist-info/top_level.txt
SML_matrix_completion-0.2.dist-info/RECORD
