Metadata-Version: 2.1
Name: SML-matrix-completion
Version: 0.2
Summary: matrix_completion
Home-page: UNKNOWN
Author: Hanh Huyen
License: LICENSE.txt
Platform: UNKNOWN
Classifier: Programming Language :: Python :: 3.9
Classifier: License :: OSI Approved :: MIT License
